CHANGES.rst
LICENSE
MANIFEST.in
README.rst
setup.cfg
setup.py
tox.ini
docs/CHANGES.rst
docs/README.rst
docs/conf.py
docs/index.rst
docs/_static/.keep
docs/_templates/.keep
src/jt/__init__.py
src/jt/jcc.cfg
src/jt/jcc/__about__.py
src/jt/jcc/__main__.py
src/jt/jcc/_java/__init__.py
src/jt/jcc/_java/class2py.py
src/jt/jcc/_java/org/__init__.py
src/jt/jcc/_java/org/apache/__init__.py
src/jt/jcc/_platform/__init__.py
src/jtypes.jcc.egg-info/PKG-INFO
src/jtypes.jcc.egg-info/SOURCES.txt
src/jtypes.jcc.egg-info/dependency_links.txt
src/jtypes.jcc.egg-info/namespace_packages.txt
src/jtypes.jcc.egg-info/requires.txt
src/jtypes.jcc.egg-info/top_level.txt
src/jtypes.jcc.egg-info/zip-safe
tests/__init__.py
tests/__main__.py
tests/run.py
tests/java/org/apache/jcc/dummy.java
tests/python/__init__.py